fcmenu/Chrome_Session.py
fcmenu/__init__.py
fcmenu-0.0.3.dist-info/METADATA
fcmenu-0.0.3.dist-info/WHEEL
fcmenu-0.0.3.dist-info/top_level.txt
fcmenu-0.0.3.dist-info/RECORD
